{
  "374": {
    "surah_number": [
    26
],
    "pageData": [
      { "line_number": 1, "line_type": "ayah", "first_word_id": 51147, "last_word_id": 51155, "text": null, "is_centered": false },
      { "line_number": 2, "line_type": "ayah", "first_word_id": 51156, "last_word_id": 51174, "text": null, "is_centered": false },
      { "line_number": 3, "line_type": "ayah", "first_word_id": 51175, "last_word_id": 51180, "text": null, "is_centered": false },
      { "line_number": 4, "line_type": "ayah", "first_word_id": 51181, "last_word_id": 51191, "text": null, "is_centered": false },
      { "line_number": 5, "line_type": "ayah", "first_word_id": 51192, "last_word_id": 51202, "text": null, "is_centered": false },
      { "line_number": 6, "line_type": "ayah", "first_word_id": 51203, "last_word_id": 51212, "text": null, "is_centered": false },
      { "line_number": 7, "line_type": "ayah", "first_word_id": 51213, "last_word_id": 51222, "text": null, "is_centered": false },
      { "line_number": 8, "line_type": "ayah", "first_word_id": 51223, "last_word_id": 51235, "text": null, "is_centered": false },
      { "line_number": 9, "line_type": "ayah", "first_word_id": 51236, "last_word_id": 51243, "text": null, "is_centered": false },
      { "line_number": 10, "line_type": "ayah", "first_word_id": 51244, "last_word_id": 51256, "text": null, "is_centered": false },
      { "line_number": 11, "line_type": "ayah", "first_word_id": 51257, "last_word_id": 51268, "text": null, "is_centered": false },
      { "line_number": 12, "line_type": "ayah", "first_word_id": 51269, "last_word_id": 51280, "text": null, "is_centered": false },
      { "line_number": 13, "line_type": "ayah", "first_word_id": 51281, "last_word_id": 51290, "text": null, "is_centered": false },
      { "line_number": 14, "line_type": "ayah", "first_word_id": 51291, "last_word_id": 51297, "text": null, "is_centered": false },
      { "line_number": 15, "line_type": "ayah", "first_word_id": 51298, "last_word_id": 51307, "text": null, "is_centered": false }
    ],
    "ayahData": [
      { "surahID": 26, "ayahID": 160, "ayah_begin": 51147, "ayah_end": 51151, "jozz": 19 },
      { "surahID": 26, "ayahID": 161, "ayah_begin": 51152, "ayah_end": 51159, "jozz": 19 },
      { "surahID": 26, "ayahID": 162, "ayah_begin": 51160, "ayah_end": 51164, "jozz": 19 },
      { "surahID": 26, "ayahID": 163, "ayah_begin": 51165, "ayah_end": 51168, "jozz": 19 },
      { "surahID": 26, "ayahID": 164, "ayah_begin": 51169, "ayah_end": 51180, "jozz": 19 },
      { "surahID": 26, "ayahID": 165, "ayah_begin": 51181, "ayah_end": 51185, "jozz": 19 },
      { "surahID": 26, "ayahID": 166, "ayah_begin": 51186, "ayah_end": 51197, "jozz": 19 },
      { "surahID": 26, "ayahID": 167, "ayah_begin": 51198, "ayah_end": 51206, "jozz": 19 },
      { "surahID": 26, "ayahID": 168, "ayah_begin": 51207, "ayah_end": 51212, "jozz": 19 },
      { "surahID": 26, "ayahID": 169, "ayah_begin": 51213, "ayah_end": 51218, "jozz": 19 },
      { "surahID": 26, "ayahID": 170, "ayah_begin": 51219, "ayah_end": 51222, "jozz": 19 },
      { "surahID": 26, "ayahID": 171, "ayah_begin": 51223, "ayah_end": 51227, "jozz": 19 },
      { "surahID": 26, "ayahID": 172, "ayah_begin": 51228, "ayah_end": 51231, "jozz": 19 },
      { "surahID": 26, "ayahID": 173, "ayah_begin": 51232, "ayah_end": 51238, "jozz": 19 },
      { "surahID": 26, "ayahID": 174, "ayah_begin": 51239, "ayah_end": 51247, "jozz": 19 },
      { "surahID": 26, "ayahID": 175, "ayah_begin": 51248, "ayah_end": 51253, "jozz": 19 },
      { "surahID": 26, "ayahID": 176, "ayah_begin": 51254, "ayah_end": 51258, "jozz": 19 },
      { "surahID": 26, "ayahID": 177, "ayah_begin": 51259, "ayah_end": 51265, "jozz": 19 },
      { "surahID": 26, "ayahID": 178, "ayah_begin": 51266, "ayah_end": 51270, "jozz": 19 },
      { "surahID": 26, "ayahID": 179, "ayah_begin": 51271, "ayah_end": 51274, "jozz": 19 },
      { "surahID": 26, "ayahID": 180, "ayah_begin": 51275, "ayah_end": 51286, "jozz": 19 },
      { "surahID": 26, "ayahID": 181, "ayah_begin": 51287, "ayah_end": 51293, "jozz": 19 },
      { "surahID": 26, "ayahID": 182, "ayah_begin": 51294, "ayah_end": 51297, "jozz": 19 },
      { "surahID": 26, "ayahID": 183, "ayah_begin": 51298, "ayah_end": 51307, "jozz": 19 }
    ],
    "wordData": {
    "51147": "‏‏‏‏",
    "51148": "‏‏‏",
    "51149": "‏‏‏",
    "51150": "‏‏‏‏‏‏‏",
    "51151": "‏",
    "51152": "‏‏",
    "51153": "‏‏‏",
    "51154": "‏‏‏",
    "51155": "‏‏‏‏‏",
    "51156": "‏‏‏",
    "51157": "‏‏",
    "51158": "‏‏‏‏‏",
    "51159": "‏",
    "51160": "‏‏",
    "51161": "‏‏‏",
    "51162": "‏‏‏‏",
    "51163": "‏‏‏",
    "51164": "‏",
    "51165": "‏‏‏‏‏‏",
    "51166": "‏‏",
    "51167": "‏‏‏‏‏‏‏",
    "51168": "‏",
    "51169": "‏‏‏",
    "51170": "‏‏‏‏‏",
    "51171": "‏‏‏‏",
    "51172": "‏‏",
    "51173": "‏‏‏‏",
    "51174": "‏‏",
    "51175": "‏‏‏‏",
    "51176": "‏‏",
    "51177": "‏",
    "51178": "‏‏",
    "51179": "‏‏‏‏‏‏",
    "51180": "‏",
    "51181": "‏‏‏‏‏‏",
    "51182": "‏‏‏‏‏‏",
    "51183": "‏‏",
    "51184": "‏‏‏‏‏‏",
    "51185": "‏",
    "51186": "‏‏‏‏‏‏‏",
    "51187": "‏‏",
    "51188": "‏‏‏",
    "51189": "‏‏‏",
    "51190": "‏‏‏‏",
    "51191": "‏‏",
    "51192": "‏‏‏‏‏‏‏‏",
    "51193": "‏‏",
    "51194": "‏‏‏‏",
    "51195": "‏‏‏",
    "51196": "‏‏‏‏",
    "51197": "‏",
    "51198": "‏‏‏‏‏",
    "51199": "‏‏",
    "51200": "‏‏",
    "51201": "‏‏‏‏",
    "51202": "‏‏‏‏",
    "51203": "‏‏‏‏‏",
    "51204": "‏‏",
    "51205": "‏‏‏‏‏‏‏",
    "51206": "‏",
    "51207": "‏‏‏",
    "51208": "‏‏",
    "51209": "‏‏‏‏‏‏",
    "51210": "‏‏",
    "51211": "‏‏‏‏‏‏",
    "51212": "‏",
    "51213": "‏‏",
    "51214": "‏‏",
    "51215": "‏‏‏‏",
    "51216": "‏‏‏",
    "51217": "‏‏‏‏‏‏",
    "51218": "‏",
    "51219": "‏‏‏‏‏‏",
    "51220": "‏‏‏‏‏‏",
    "51221": "‏‏‏‏",
    "51222": "‏",
    "51223": "‏‏",
    "51224": "‏‏‏‏‏‏",
    "51225": "‏",
    "51226": "‏‏‏‏‏‏‏",
    "51227": "‏",
    "51228": "‏‏",
    "51229": "‏‏‏‏‏",
    "51230": "‏‏‏‏‏‏",
    "51231": "‏",
    "51232": "‏‏‏‏‏‏‏",
    "51233": "‏‏‏‏‏",
    "51234": "‏‏‏‏‏",
    "51235": "‏‏‏‏",
    "51236": "‏‏‏",
    "51237": "‏‏‏‏‏‏‏‏",
    "51238": "‏",
    "51239": "‏‏",
    "51240": "‏",
    "51241": "‏‏‏",
    "51242": "‏‏‏‏‏",
    "51243": "‏‏‏",
    "51244": "‏‏",
    "51245": "‏‏‏‏‏‏",
    "51246": "‏‏‏‏‏",
    "51247": "‏",
    "51248": "‏‏",
    "51249": "‏‏‏",
    "51250": "‏‏‏",
    "51251": "‏‏‏‏‏‏",
    "51252": "‏‏‏‏‏‏",
    "51253": "‏",
    "51254": "‏‏‏",
    "51255": "‏‏‏‏",
    "51256": "‏‏‏‏",
    "51257": "‏‏‏‏‏‏‏",
    "51258": "‏",
    "51259": "‏‏",
    "51260": "‏‏‏",
    "51261": "‏‏‏",
    "51262": "‏‏‏‏",
    "51263": "‏‏",
    "51264": "‏‏‏‏‏",
    "51265": "‏",
    "51266": "‏‏",
    "51267": "‏‏‏",
    "51268": "‏‏‏‏",
    "51269": "‏‏‏",
    "51270": "‏",
    "51271": "‏‏‏‏‏‏",
    "51272": "‏‏",
    "51273": "‏‏‏‏‏‏‏",
    "51274": "‏",
    "51275": "‏‏‏",
    "51276": "‏‏‏‏‏",
    "51277": "‏‏‏‏",
    "51278": "‏‏",
    "51279": "‏‏‏‏",
    "51280": "‏‏",
    "51281": "‏‏‏‏",
    "51282": "‏‏",
    "51283": "‏",
    "51284": "‏‏",
    "51285": "‏‏‏‏‏‏",
    "51286": "‏",
    "51287": "‏‏‏‏‏‏",
    "51288": "‏‏‏‏‏",
    "51289": "‏‏",
    "51290": "‏‏‏‏‏‏",
    "51291": "‏‏",
    "51292": "‏‏‏‏‏‏‏‏",
    "51293": "‏",
    "51294": "‏‏‏‏‏‏",
    "51295": "‏‏‏‏‏‏‏‏",
    "51296": "‏‏‏‏‏‏‏‏",
    "51297": "‏",
    "51298": "‏‏",
    "51299": "‏‏‏‏‏‏",
    "51300": "‏‏‏‏",
    "51301": "‏‏‏‏‏‏‏",
    "51302": "‏‏",
    "51303": "‏‏‏‏‏",
    "51304": "‏",
    "51305": "‏‏‏‏",
    "51306": "‏‏‏‏‏‏",
    "51307": "‏"
}
  }
}
