{
  "198": {
    "surah_number": [
    9
],
    "pageData": [
      { "line_number": 1, "line_type": "ayah", "first_word_id": 25057, "last_word_id": 25064, "text": null, "is_centered": false },
      { "line_number": 2, "line_type": "ayah", "first_word_id": 25065, "last_word_id": 25070, "text": null, "is_centered": false },
      { "line_number": 3, "line_type": "ayah", "first_word_id": 25071, "last_word_id": 25077, "text": null, "is_centered": false },
      { "line_number": 4, "line_type": "ayah", "first_word_id": 25078, "last_word_id": 25084, "text": null, "is_centered": false },
      { "line_number": 5, "line_type": "ayah", "first_word_id": 25085, "last_word_id": 25090, "text": null, "is_centered": false },
      { "line_number": 6, "line_type": "ayah", "first_word_id": 25091, "last_word_id": 25099, "text": null, "is_centered": false },
      { "line_number": 7, "line_type": "ayah", "first_word_id": 25100, "last_word_id": 25104, "text": null, "is_centered": false },
      { "line_number": 8, "line_type": "ayah", "first_word_id": 25105, "last_word_id": 25111, "text": null, "is_centered": false },
      { "line_number": 9, "line_type": "ayah", "first_word_id": 25112, "last_word_id": 25117, "text": null, "is_centered": false },
      { "line_number": 10, "line_type": "ayah", "first_word_id": 25118, "last_word_id": 25124, "text": null, "is_centered": false },
      { "line_number": 11, "line_type": "ayah", "first_word_id": 25125, "last_word_id": 25130, "text": null, "is_centered": false },
      { "line_number": 12, "line_type": "ayah", "first_word_id": 25131, "last_word_id": 25138, "text": null, "is_centered": false },
      { "line_number": 13, "line_type": "ayah", "first_word_id": 25139, "last_word_id": 25146, "text": null, "is_centered": false },
      { "line_number": 14, "line_type": "ayah", "first_word_id": 25147, "last_word_id": 25154, "text": null, "is_centered": false },
      { "line_number": 15, "line_type": "ayah", "first_word_id": 25155, "last_word_id": 25162, "text": null, "is_centered": false }
    ],
    "ayahData": [
      { "surahID": 9, "ayahID": 69, "ayah_begin": 25057, "ayah_end": 25088, "jozz": 10 },
      { "surahID": 9, "ayahID": 70, "ayah_begin": 25089, "ayah_end": 25114, "jozz": 10 },
      { "surahID": 9, "ayahID": 71, "ayah_begin": 25115, "ayah_end": 25138, "jozz": 10 },
      { "surahID": 9, "ayahID": 72, "ayah_begin": 25139, "ayah_end": 25162, "jozz": 10 }
    ],
    "wordData": {
    "25057": {
        "glyph": "‏‏‏‏",
        "emlaey": "كالذين"
    },
    "25058": {
        "glyph": "‏‏",
        "emlaey": "من"
    },
    "25059": {
        "glyph": "‏‏‏‏‏",
        "emlaey": "قبلكم"
    },
    "25060": {
        "glyph": "‏‏‏‏",
        "emlaey": "كانوا"
    },
    "25061": {
        "glyph": "‏‏‏",
        "emlaey": "أشد"
    },
    "25062": {
        "glyph": "‏‏‏‏",
        "emlaey": "منكم"
    },
    "25063": {
        "glyph": "‏‏‏",
        "emlaey": "قوة"
    },
    "25064": {
        "glyph": "‏‏‏‏‏",
        "emlaey": "وأكثر"
    },
    "25065": {
        "glyph": "‏‏‏‏",
        "emlaey": "أموالا"
    },
    "25066": {
        "glyph": "‏‏‏‏‏‏",
        "emlaey": "وأولادا"
    },
    "25067": {
        "glyph": "‏‏‏‏‏‏‏‏‏",
        "emlaey": "فاستمتعوا"
    },
    "25068": {
        "glyph": "‏‏‏‏‏",
        "emlaey": "بخلاقهم"
    },
    "25069": {
        "glyph": "‏‏‏‏‏‏‏‏‏",
        "emlaey": "فاستمتعتم"
    },
    "25070": {
        "glyph": "‏‏‏‏‏",
        "emlaey": "بخلاقكم"
    },
    "25071": {
        "glyph": "‏‏‏",
        "emlaey": "كما"
    },
    "25072": {
        "glyph": "‏‏‏‏‏‏",
        "emlaey": "استمتع"
    },
    "25073": {
        "glyph": "‏‏‏‏",
        "emlaey": "الذين"
    },
    "25074": {
        "glyph": "‏‏",
        "emlaey": "من"
    },
    "25075": {
        "glyph": "‏‏‏‏‏",
        "emlaey": "قبلكم"
    },
    "25076": {
        "glyph": "‏‏‏‏‏",
        "emlaey": "بخلاقهم"
    },
    "25077": {
        "glyph": "‏‏‏‏‏",
        "emlaey": "وخضتم"
    },
    "25078": {
        "glyph": "‏‏‏",
        "emlaey": "كالذي"
    },
    "25079": {
        "glyph": "‏‏‏‏‏",
        "emlaey": "خاضوا"
    },
    "25080": {
        "glyph": "‏‏‏‏‏",
        "emlaey": "أولئك"
    },
    "25081": {
        "glyph": "‏‏‏‏",
        "emlaey": "حبطت"
    },
    "25082": {
        "glyph": "‏‏‏‏‏‏",
        "emlaey": "أعمالهم"
    },
    "25083": {
        "glyph": "‏",
        "emlaey": "في"
    },
    "25084": {
        "glyph": "‏‏‏‏‏",
        "emlaey": "الدنيا"
    },
    "25085": {
        "glyph": "‏‏‏‏‏‏‏",
        "emlaey": "والآخرة"
    },
    "25086": {
        "glyph": "‏‏‏‏‏‏",
        "emlaey": "وأولئك"
    },
    "25087": {
        "glyph": "‏‏",
        "emlaey": "هم"
    },
    "25088": {
        "glyph": "‏‏‏‏‏‏‏‏",
        "emlaey": "الخاسرون"
    },
    "25089": {
        "glyph": "‏‏‏",
        "emlaey": "ألم"
    },
    "25090": {
        "glyph": "‏‏‏‏‏",
        "emlaey": "يأتهم"
    },
    "25091": {
        "glyph": "‏‏‏",
        "emlaey": "نبأ"
    },
    "25092": {
        "glyph": "‏‏‏‏",
        "emlaey": "الذين"
    },
    "25093": {
        "glyph": "‏‏",
        "emlaey": "من"
    },
    "25094": {
        "glyph": "‏‏‏‏‏",
        "emlaey": "قبلهم"
    },
    "25095": {
        "glyph": "‏‏‏",
        "emlaey": "قوم"
    },
    "25096": {
        "glyph": "‏‏‏",
        "emlaey": "نوح"
    },
    "25097": {
        "glyph": "‏‏‏",
        "emlaey": "وعاد"
    },
    "25098": {
        "glyph": "‏‏‏‏‏",
        "emlaey": "وثمود"
    },
    "25099": {
        "glyph": "‏‏‏‏",
        "emlaey": "وقوم"
    },
    "25100": {
        "glyph": "‏‏‏‏‏‏",
        "emlaey": "إبراهيم"
    },
    "25101": {
        "glyph": "‏‏‏‏‏",
        "emlaey": "وأصحاب"
    },
    "25102": {
        "glyph": "‏‏‏‏",
        "emlaey": "مدين"
    },
    "25103": {
        "glyph": "‏‏‏‏‏‏‏‏‏‏",
        "emlaey": "والمؤتفكات"
    },
    "25104": {
        "glyph": "‏‏‏‏‏",
        "emlaey": "أتتهم"
    },
    "25105": {
        "glyph": "‏‏‏‏‏",
        "emlaey": "رسلهم"
    },
    "25106": {
        "glyph": "‏‏‏‏‏‏‏",
        "emlaey": "بالبينات"
    },
    "25107": {
        "glyph": "‏‏‏",
        "emlaey": "فما"
    },
    "25108": {
        "glyph": "‏‏",
        "emlaey": "كان"
    },
    "25109": {
        "glyph": "‏‏",
        "emlaey": "الله"
    },
    "25110": {
        "glyph": "‏‏‏‏‏‏",
        "emlaey": "ليظلمهم"
    },
    "25111": {
        "glyph": "‏‏‏‏",
        "emlaey": "ولكن"
    },
    "25112": {
        "glyph": "‏‏‏‏",
        "emlaey": "كانوا"
    },
    "25113": {
        "glyph": "‏‏‏‏‏‏",
        "emlaey": "أنفسهم"
    },
    "25114": {
        "glyph": "‏‏‏‏‏‏",
        "emlaey": "يظلمون"
    },
    "25115": {
        "glyph": "‏‏‏‏‏‏‏‏‏",
        "emlaey": "والمؤمنون"
    },
    "25116": {
        "glyph": "‏‏‏‏‏‏‏‏",
        "emlaey": "والمؤمنات"
    },
    "25117": {
        "glyph": "‏‏‏‏‏",
        "emlaey": "بعضهم"
    },
    "25118": {
        "glyph": "‏‏‏‏‏",
        "emlaey": "أولياء"
    },
    "25119": {
        "glyph": "‏‏‏‏",
        "emlaey": "بعض"
    },
    "25120": {
        "glyph": "‏‏‏‏‏‏‏",
        "emlaey": "يأمرون"
    },
    "25121": {
        "glyph": "‏‏‏‏‏‏‏‏‏",
        "emlaey": "بالمعروف"
    },
    "25122": {
        "glyph": "‏‏‏‏‏‏",
        "emlaey": "وينهون"
    },
    "25123": {
        "glyph": "‏‏",
        "emlaey": "عن"
    },
    "25124": {
        "glyph": "‏‏‏‏‏‏",
        "emlaey": "المنكر"
    },
    "25125": {
        "glyph": "‏‏‏‏‏‏‏",
        "emlaey": "ويقيمون"
    },
    "25126": {
        "glyph": "‏‏‏‏‏‏",
        "emlaey": "الصلاة"
    },
    "25127": {
        "glyph": "‏‏‏‏‏‏",
        "emlaey": "ويؤتون"
    },
    "25128": {
        "glyph": "‏‏‏‏‏‏",
        "emlaey": "الزكاة"
    },
    "25129": {
        "glyph": "‏‏‏‏‏‏‏",
        "emlaey": "ويطيعون"
    },
    "25130": {
        "glyph": "‏‏",
        "emlaey": "الله"
    },
    "25131": {
        "glyph": "‏‏‏‏‏‏‏‏",
        "emlaey": "ورسوله"
    },
    "25132": {
        "glyph": "‏‏‏‏‏",
        "emlaey": "أولئك"
    },
    "25133": {
        "glyph": "‏‏‏‏‏‏",
        "emlaey": "سيرحمهم"
    },
    "25134": {
        "glyph": "‏‏‏",
        "emlaey": "الله"
    },
    "25135": {
        "glyph": "‏‏",
        "emlaey": "إن"
    },
    "25136": {
        "glyph": "‏‏",
        "emlaey": "الله"
    },
    "25137": {
        "glyph": "‏‏‏‏",
        "emlaey": "عزيز"
    },
    "25138": {
        "glyph": "‏‏‏‏",
        "emlaey": "حكيم"
    },
    "25139": {
        "glyph": "‏‏‏",
        "emlaey": "وعد"
    },
    "25140": {
        "glyph": "‏‏",
        "emlaey": "الله"
    },
    "25141": {
        "glyph": "‏‏‏‏‏‏‏",
        "emlaey": "المؤمنين"
    },
    "25142": {
        "glyph": "‏‏‏‏‏‏‏‏",
        "emlaey": "والمؤمنات"
    },
    "25143": {
        "glyph": "‏‏‏",
        "emlaey": "جنات"
    },
    "25144": {
        "glyph": "‏‏‏",
        "emlaey": "تجري"
    },
    "25145": {
        "glyph": "‏‏",
        "emlaey": "من"
    },
    "25146": {
        "glyph": "‏‏‏‏",
        "emlaey": "تحتها"
    },
    "25147": {
        "glyph": "‏‏‏‏‏",
        "emlaey": "الأنهار"
    },
    "25148": {
        "glyph": "‏‏‏‏",
        "emlaey": "خالدين"
    },
    "25149": {
        "glyph": "‏‏‏‏",
        "emlaey": "فيها"
    },
    "25150": {
        "glyph": "‏‏‏‏‏",
        "emlaey": "ومساكن"
    },
    "25151": {
        "glyph": "‏‏‏‏",
        "emlaey": "طيبة"
    },
    "25152": {
        "glyph": "‏",
        "emlaey": "في"
    },
    "25153": {
        "glyph": "‏‏‏",
        "emlaey": "جنات"
    },
    "25154": {
        "glyph": "‏‏‏‏",
        "emlaey": "عدن"
    },
    "25155": {
        "glyph": "‏‏‏‏‏‏",
        "emlaey": "ورضوان"
    },
    "25156": {
        "glyph": "‏‏",
        "emlaey": "من"
    },
    "25157": {
        "glyph": "‏‏",
        "emlaey": "الله"
    },
    "25158": {
        "glyph": "‏‏‏‏‏",
        "emlaey": "أكبر"
    },
    "25159": {
        "glyph": "‏‏‏",
        "emlaey": "ذلك"
    },
    "25160": {
        "glyph": "‏‏",
        "emlaey": "هو"
    },
    "25161": {
        "glyph": "‏‏‏‏‏‏",
        "emlaey": "الفوز"
    },
    "25162": {
        "glyph": "‏‏‏‏‏‏",
        "emlaey": "العظيم"
    }
}
  }
}
